Workbook

Sheet BASE_CALCULADA
A1: id_os | B1: id_cliente | C1: id_veiculo | D1: id_mecanico | E1: id_peca | F1: id_servico | G1: id_tempo | H1: quantidade_pecas | I1: custo_peca | J1: valor_servico | K1: valor_total | L1: lucro | M1: tempo_execucao_horas | N1: status | O1: preco_base_servico | P1: preco_unitario_peca | Q1: custo_unitario_peca | R1: valor_pecas_calc | S1: valor_mao_obra_calc | T1: valor_bruto_calc | U1: desconto_calc | V1: valor_total_calc | W1: checagem | X1: categoria_servico
A2: 1 | B2: 372 | C2: 1190 | D2: 978 | E2: 87 | F2: 76 | G2: 951 | H2: 4 | I2: 1382.84 | J2: 258.16 | K2: 2935.36 | L2: 1429.59 | M2: 4.7 | N2: Concluída | O2: =VLOOKUP(F2,DIM_SERVICO!$A$2:$D$151,4,FALSE()) -> 258.16 | P2: =VLOOKUP(E2,DIM_PECA!$A$2:$F$501,6,FALSE()) -> 669.3 | Q2: =VLOOKUP(E2,DIM_PECA!$A$2:$F$501,5,FALSE()) -> 345.71 | R2: =H2*P2 -> 2677.2 | S2: =O2*M2 -> 1213.352 | T2: =R2+S2 -> 3890.552 | U2: =T2-K2 -> 955.192 | V2: =R2+S2-U2 -> 2935.36 | W2: =IF(ROUND(V2-K2,2)=0,"OK","ERRO") -> OK | X2: =VLOOKUP(F2,DIM_SERVICO!$A$2:$D$151,3,FALSE()) -> Diagnóstico
A3: 2 | B3: 872 | C3: 1073 | D3: 730 | E3: 71 | F3: 27 | G3: 7 | H3: 4 | I3: 117.92 | J3: 662.68 | K3: 745.42 | L3: 370.63 | M3: 6.6 | N3: Concluída | O3: =VLOOKUP(F3,DIM_SERVICO!$A$2:$D$151,4,FALSE()) -> 662.68 | P3: =VLOOKUP(E3,DIM_PECA!$A$2:$F$501,6,FALSE()) -> 41.39 | Q3: =VLOOKUP(E3,DIM_PECA!$A$2:$F$501,5,FALSE()) -> 29.48 | R3: =H3*P3 -> 165.56 | S3: =O3*M3 -> 4373.688 | T3: =R3+S3 -> 4539.248 | U3: =T3-K3 -> 3793.828 | V3: =R3+S3-U3 -> 745.42 | W3: =IF(ROUND(V3-K3,2)=0,"OK","ERRO") -> OK | X3: =VLOOKUP(F3,DIM_SERVICO!$A$2:$D$151,3,FALSE()) -> Revisão
A4: 3 | B4: 704 | C4: 1405 | D4: 317 | E4: 259 | F4: 18 | G4: 1801 | H4: 4 | I4: 2048.04 | J4: 1667.15 | K4: 4814.82 | L4: 1867.37 | M4: 0.6 | N4: Concluída | O4: =VLOOKUP(F4,DIM_SERVICO!$A$2:$D$151,4,FALSE()) -> 1667.15 | P4: =VLOOKUP(E4,DIM_PECA!$A$2:$F$501,6,FALSE()) -> 850.27 | Q4: =VLOOKUP(E4,DIM_PECA!$A$2:$F$501,5,FALSE()) -> 512.01 | R4: =H4*P4 -> 3401.08 | S4: =O4*M4 -> 1000.29 | T4: =R4+S4 -> 4401.37 | U4: =T4-K4 -> -413.45 | V4: =R4+S4-U4 -> 4814.82 | W4: =IF(ROUND(V4-K4,2)=0,"OK","ERRO") -> OK | X4: =VLOOKUP(F4,DIM_SERVICO!$A$2:$D$151,3,FALSE()) -> Elétrica
A5: 4 | B5: 480 | C5: 775 | D5: 734 | E5: 438 | F5: 130 | G5: 1395 | H5: 1 | I5: 1119.28 | J5: 170.79 | K5: 2248.82 | L5: 1053.15 | M5: 4.1 | N5: Concluída | O5: =VLOOKUP(F5,DIM_SERVICO!$A$2:$D$151,4,FALSE()) -> 170.79 | P5: =VLOOKUP(E5,DIM_PECA!$A$2:$F$501,6,FALSE()) -> 2078.03 | Q5: =VLOOKUP(E5,DIM_PECA!$A$2:$F$501,5,FALSE()) -> 1119.28 | R5: =H5*P5 -> 2078.03 | S5: =O5*M5 -> 700.239 | T5: =R5+S5 -> 2778.269 | U5: =T5-K5 -> 529.449 | V5: =R5+S5-U5 -> 2248.82 | W5: =IF(ROUND(V5-K5,2)=0,"OK","ERRO") -> OK | X5: =VLOOKUP(F5,DIM_SERVICO!$A$2:$D$151,3,FALSE()) -> Pintura
A6: 5 | B6: 1359 | C6: 335 | D6: 682 | E6: 88 | F6: 140 | G6: 1377 | H6: 3 | I6: 567.09 | J6: 1109.33 | K6: 2236.8 | L6: 1209.89 | M6: 5.4 | N6: Concluída | O6: =VLOOKUP(F6,DIM_SERVICO!$A$2:$D$151,4,FALSE()) -> 1109.33 | P6: =VLOOKUP(E6,DIM_PECA!$A$2:$F$501,6,FALSE()) -> 391.04 | Q6: =VLOOKUP(E6,DIM_PECA!$A$2:$F$501,5,FALSE()) -> 189.03 | R6: =H6*P6 -> 1173.12 | S6: =O6*M6 -> 5990.382 | T6: =R6+S6 -> 7163.502 | U6: =T6-K6 -> 4926.702 | V6: =R6+S6-U6 -> 2236.8 | W6: =IF(ROUND(V6-K6,2)=0,"OK","ERRO") -> OK | X6: =VLOOKUP(F6,DIM_SERVICO!$A$2:$D$151,3,FALSE()) -> Revisão
A7: 6 | B7: 863 | C7: 154 | D7: 819 | E7: 306 | F7: 35 | G7: 322 | H7: 3 | I7: 793.41 | J7: 1082.38 | K7: 2711.95 | L7: 1395.57 | M7: 9.5 | N7: Em Andamento | O7: =VLOOKUP(F7,DIM_SERVICO!$A$2:$D$151,4,FALSE()) -> 1082.38 | P7: =VLOOKUP(E7,DIM_PECA!$A$2:$F$501,6,FALSE()) -> 543.19 | Q7: =VLOOKUP(E7,DIM_PECA!$A$2:$F$501,5,FALSE()) -> 264.47 | R7: =H7*P7 -> 1629.57 | S7: =O7*M7 -> 10282.61 | T7: =R7+S7 -> 11912.18 | U7: =T7-K7 -> 9200.23 | V7: =R7+S7-U7 -> 2711.95 | W7: =IF(ROUND(V7-K7,2)=0,"OK","ERRO") -> OK | X7: =VLOOKUP(F7,DIM_SERVICO!$A$2:$D$151,3,FALSE()) -> Diagnóstico
A8: 7 | B8: 258 | C8: 1239 | D8: 809 | E8: 5 | F8: 56 | G8: 253 | H8: 1 | I8: 928.46 | J8: 251.62 | K8: 1705.56 | L8: 685.9 | M8: 3.5 | N8: Concluída | O8: =VLOOKUP(F8,DIM_SERVICO!$A$2:$D$151,4,FALSE()) -> 251.62 | P8: =VLOOKUP(E8,DIM_PECA!$A$2:$F$501,6,FALSE()) -> 1543.71 | Q8: =VLOOKUP(E8,DIM_PECA!$A$2:$F$501,5,FALSE()) -> 928.46 | R8: =H8*P8 -> 1543.71 | S8: =O8*M8 -> 880.67 | T8: =R8+S8 -> 2424.38 | U8: =T8-K8 -> 718.82 | V8: =R8+S8-U8 -> 1705.56 | W8: =IF(ROUND(V8-K8,2)=0,"OK","ERRO") -> OK | X8: =VLOOKUP(F8,DIM_SERVICO!$A$2:$D$151,3,FALSE()) -> Revisão
A9: 8 | B9: 953 | C9: 1485 | D9: 7 | E9: 317 | F9: 140 | G9: 1742 | H9: 3 | I9: 155.61 | J9: 1109.33 | K9: 1291.28 | L9: 690.06 | M9: 11.8 | N9: Em Andamento | O9: =VLOOKUP(F9,DIM_SERVICO!$A$2:$D$151,4,FALSE()) -> 1109.33 | P9: =VLOOKUP(E9,DIM_PECA!$A$2:$F$501,6,FALSE()) -> 98.08 | Q9: =VLOOKUP(E9,DIM_PECA!$A$2:$F$501,5,FALSE()) -> 51.87 | R9: =H9*P9 -> 294.24 | S9: =O9*M9 -> 13090.094 | T9: =R9+S9 -> 13384.334 | U9: =T9-K9 -> 12093.054 | V9: =R9+S9-U9 -> 1291.28 | W9: =IF(ROUND(V9-K9,2)=0,"OK","ERRO") -> OK | X9: =VLOOKUP(F9,DIM_SERVICO!$A$2:$D$151,3,FALSE()) -> Revisão
A10: 9 | B10: 357 | C10: 1129 | D10: 1033 | E10: 23 | F10: 70 | G10: 1094 | H10: 2 | I10: 469.86 | J10: 688.79 | K10: 1662.25 | L10: 916.19 | M10: 4.2 | N10: Aguardando Peça | O10: =VLOOKUP(F10,DIM_SERVICO!$A$2:$D$151,4,FALSE()) -> 688.79 | P10: =VLOOKUP(E10,DIM_PECA!$A$2:$F$501,6,FALSE()) -> 486.73 | Q10: =VLOOKUP(E10,DIM_PECA!$A$2:$F$501,5,FALSE()) -> 234.93 | R10: =H10*P10 -> 973.46 | S10: =O10*M10 -> 2892.918 | T10: =R10+S10 -> 3866.378 | U10: =T10-K10 -> 2204.128 | V10: =R10+S10-U10 -> 1662.25 | W10: =IF(ROUND(V10-K10,2)=0,"OK","ERRO") -> OK | X10: =VLOOKUP(F10,DIM_SERVICO!$A$2:$D$151,3,FALSE()) -> Freios
A11: 10 | B11: 812 | C11: 773 | D11: 832 | E11: 469 | F11: 35 | G11: 793 | H11: 1 | I11: 431.81 | J11: 1082.38 | K11: 1989.37 | L11: 1157.09 | M11: 8.2 | N11: Concluída | O11: =VLOOKUP(F11,DIM_SERVICO!$A$2:$D$151,4,FALSE()) -> 1082.38 | P11: =VLOOKUP(E11,DIM_PECA!$A$2:$F$501,6,FALSE()) -> 906.99 | Q11: =VLOOKUP(E11,DIM_PECA!$A$2:$F$501,5,FALSE()) -> 431.81 | R11: =H11*P11 -> 906.99 | S11: =O11*M11 -> 8875.516 | T11: =R11+S11 -> 9782.506 | U11: =T11-K11 -> 7793.136 | V11: =R11+S11-U11 -> 1989.37 | W11: =IF(ROUND(V11-K11,2)=0,"OK","ERRO") -> OK | X11: =VLOOKUP(F11,DIM_SERVICO!$A$2:$D$151,3,FALSE()) -> Diagnóstico
A12: 11 | B12: 1498 | C12: 1033 | D12: 58 | E12: 217 | F12: 109 | G12: 1532 | H12: 4 | I12: 2754.08 | J12: 1418.47 | K12: 6900.47 | L12: 3634.01 | M12: 7.5 | N12: Cancelada | O12: =VLOOKUP(F12,DIM_SERVICO!$A$2:$D$151,4,FALSE()) -> 1418.47 | P12: =VLOOKUP(E12,DIM_PECA!$A$2:$F$501,6,FALSE()) -> 1370.5 | Q12: =VLOOKUP(E12,DIM_PECA!$A$2:$F$501,5,FALSE()) -> 688.52 | R12: =H12*P12 -> 5482 | S12: =O12*M12 -> 10638.525 | T12: =R12+S12 -> 16120.525 | U12: =T12-K12 -> 9220.055 | V12: =R12+S12-U12 -> 6900.47 | W12: =IF(ROUND(V12-K12,2)=0,"OK","ERRO") -> OK | X12: =VLOOKUP(F12,DIM_SERVICO!$A$2:$D$151,3,FALSE()) -> Pintura
A13: 12 | B13: 613 | C13: 1184 | D13: 861 | E13: 326 | F13: 78 | G13: 456 | H13: 1 | I13: 704.6 | J13: 1647.18 | K13: 2480.82 | L13: 1035.42 | M13: 0.6 | N13: Em Andamento | O13: =VLOOKUP(F13,DIM_SERVICO!$A$2:$D$151,4,FALSE()) -> 1647.18 | P13: =VLOOKUP(E13,DIM_PECA!$A$2:$F$501,6,FALSE()) -> 964.21 | Q13: =VLOOKUP(E13,DIM_PECA!$A$2:$F$501,5,FALSE()) -> 704.6 | R13: =H13*P13 -> 964.21 | S13: =O13*M13 -> 988.308 | T13: =R13+S13 -> 1952.518 | U13: =T13-K13 -> -528.302 | V13: =R13+S13-U13 -> 2480.82 | W13: =IF(ROUND(V13-K13,2)=0,"OK","ERRO") -> OK | X13: =VLOOKUP(F13,DIM_SERVICO!$A$2:$D$151,3,FALSE()) -> Suspensão
... A1201: 1200 | B1201: 1177 | C1201: 1487 | D1201: 408 | E1201: 470 | F1201: 86 | G1201: 108 | H1201: 4 | I1201: 644.2 | J1201: 147.26 | K1201: 1231.68 | L1201: 517.43 | M1201: 4.8 | N1201: Aguardando Peça | O1201: =VLOOKUP(F1201,DIM_SERVICO!$A$2:$D$151,4,FALSE()) -> 147.26 | P1201: =VLOOKUP(E1201,DIM_PECA!$A$2:$F$501,6,FALSE()) -> 277.39 | Q1201: =VLOOKUP(E1201,DIM_PECA!$A$2:$F$501,5,FALSE()) -> 161.05 | R1201: =H1201*P1201 -> 1109.56 | S1201: =O1201*M1201 -> 706.848 | T1201: =R1201+S1201 -> 1816.408 | U1201: =T1201-K1201 -> 584.728 | V1201: =R1201+S1201-U1201 -> 1231.68 | W1201: =IF(ROUND(V1201-K1201,2)=0,"OK","ERRO") -> OK | X1201: =VLOOKUP(F1201,DIM_SERVICO!$A$2:$D$151,3,FALSE()) -> Suspensão

Sheet DIM_SERVICO
A1: id_servico | B1: descricao | C1: categoria | D1: preco_base
A2: 1 | B2: Instalação de Som Automotivo | C2: Elétrica | D2: 412.84
A3: 2 | B3: Troca de Bandeja | C3: Suspensão | D3: 1072.4
A4: 3 | B4: Pintura de Retoque | C4: Pintura | D4: 274.77
A5: 4 | B5: Troca de Óleo e Filtro | C5: Revisão | D5: 1007.95
A6: 5 | B6: Reparo de Porta | C6: Funilaria | D6: 1161.51
A7: 6 | B7: Retífica de Motor | C7: Motor | D7: 1505.67
A8: 7 | B8: Check-up de Viagem | C8: Revisão | D8: 2158.23
A9: 8 | B9: Limpeza de Bicos Injetores | C9: Motor | D9: 812.52
A10: 9 | B10: Revisão 20.000 km | C10: Revisão | D10: 1605.45
A11: 10 | B11: Inspeção Pré-Compra | C11: Diagnóstico | D11: 338.82
A12: 11 | B12: Troca de Pastilhas Dianteiras | C12: Freios | D12: 2164.78
A13: 12 | B13: Revisão 30.000 km | C13: Revisão | D13: 1399.41
... A151: 150 | B151: Revisão 20.000 km | C151: Revisão | D151: 1370.46

Sheet DIM_PECA
A1: id_peca | B1: descricao | C1: fabricante | D1: categoria | E1: custo_unitario | F1: preco_unitario
A2: 1 | B2: Correia Poly-V | C2: Varga | D2: Correias e Tensores | E2: 994.02 | F2: 1488.03
A3: 2 | B3: Platô de Embreagem | C3: Mahle | D3: Embreagem | E3: 809.69 | F3: 1213.28
A4: 3 | B4: Bateria 60Ah | C4: NGK | D4: Elétrica | E4: 59.05 | F4: 94.61
A5: 4 | B5: Coxim do Câmbio | C5: Monroe | D5: Amortecimento | E5: 816.03 | F5: 1483.6
A6: 5 | B6: Óleo Motor 5W30 | C6: Mahle | D6: Motor | E6: 928.46 | F6: 1543.71
A7: 6 | B7: Correia Dentada | C7: Continental | D7: Motor | E7: 116.1 | F7: 209.73
A8: 7 | B8: Óleo Motor 5W40 | C8: Valeo | D8: Motor | E8: 726.18 | F8: 1260.9
A9: 8 | B9: Filtro de Cabine | C9: Bosch | D9: Filtros | E9: 578.53 | F9: 1090.41
A10: 9 | B10: Platô de Embreagem | C10: Fras-le | D10: Embreagem | E10: 887.69 | F10: 1401.8
A11: 10 | B11: Mangueira do Radiador | C11: Magneti Marelli | D11: Arrefecimento | E11: 488.74 | F11: 1069.82
A12: 11 | B12: Bobina de Ignição | C12: Magneti Marelli | D12: Ignição | E12: 581.48 | F12: 958.18
A13: 12 | B13: Esticador de Correia | C13: Continental | D13: Correias e Tensores | E13: 448.12 | F13: 611.46
... A501: 500 | B501: Filtro de Óleo | C501: Continental | D501: Filtros | E501: 1133.7 | F501: 1576.52

Sheet RESUMO_KPIS
A1: RESUMO DE INDICADORES - ORDENS DE SERVIÇO
A2: Calculado a partir da aba BASE_CALCULADA
A4: Indicador | B4: Valor | C4: Fórmula utilizada
A5: Total de Ordens de Serviço (SUBTOTAL) | B5: =SUBTOTAL(103,BASE_CALCULADA!A2:A1201) -> 1200 | C5: SUBTOTAL - conta linhas visíveis (filtros)
A6: Receita Total (SOMA) | B6: =SUM(BASE_CALCULADA!K2:K1201) -> 4277277.6 | C6: SOMA do valor_total
A7: Lucro Total (SOMA) | B7: =SUM(BASE_CALCULADA!L2:L1201) -> 1898728.7 | C7: SOMA do lucro
A8: Custo Total de Peças (SOMA) | B8: =SUM(BASE_CALCULADA!I2:I1201) -> 1791334.6 | C8: SOMA do custo_peca
A9: Receita - Status Concluída (SOMASES) | B9: =SUMIFS(BASE_CALCULADA!K2:K1201,BASE_CALCULADA!N2:N1201,"Concluída") -> 2521178.7 | C9: SOMASES por status
A10: Receita - Categoria Revisão (SOMASES) | B10: =SUMIFS(BASE_CALCULADA!K2:K1201,BASE_CALCULADA!X2:X1201,"Revisão") -> 803684.53 | C10: SOMASES por categoria de serviço (coluna auxiliar X)
A11: Ticket Médio por OS (MÉDIA) | B11: =AVERAGE(BASE_CALCULADA!K2:K1201) -> 3564.398 | C11: MÉDIA do valor_total
A12: Tempo Médio de Execução em horas (MÉDIA) | B12: =AVERAGE(BASE_CALCULADA!M2:M1201) -> 6.18375 | C12: MÉDIA do tempo_execucao_horas
A13: Lucro Médio Arredondado 2 casas (ARRED+MÉDIA) | B13: =ROUND(AVERAGE(BASE_CALCULADA!L2:L1201),2) -> 1582.27 | C13: ARRED aninhado em MÉDIA
A14: Quantidade de OS Concluídas (CONT.SE) | B14: =COUNTIF(BASE_CALCULADA!N2:N1201,"Concluída") -> 692 | C14: CONT.SE por status
A15: Quantidade de OS Canceladas (CONT.SE) | B15: =COUNTIF(BASE_CALCULADA!N2:N1201,"Cancelada") -> 179 | C15: CONT.SE por status
A16: Quantidade de Checagens OK (CONT.SE) | B16: =COUNTIF(BASE_CALCULADA!W2:W1201,"OK") -> 1200 | C16: CONT.SE na coluna de auditoria
A17: Quantidade de Checagens ERRO (CONT.SE) | B17: =COUNTIF(BASE_CALCULADA!W2:W1201,"ERRO") -> 0 | C17: CONT.SE na coluna de auditoria
A18: Status de Integridade (SE) | B18: =IF(COUNTIF(BASE_CALCULADA!W2:W1201,"ERRO")=0,"BASE ÍNTEGRA","VERIFICAR ERROS") -> BASE ÍNTEGRA | C18: SE condicional sobre o total de erros

Sheet RESUMO_POR_CATEGORIA
A1: RECEITA E LUCRO POR CATEGORIA DE SERVIÇO
A3: categoria | B3: qtd_os (CONT.SE) | C3: receita_total (SOMASES) | D3: lucro_total (SOMASES) | E3: ticket_medio (SE+ARRED)
A4: Diagnóstico | B4: =COUNTIF(BASE_CALCULADA!X2:X1201,A4) -> 122 | C4: =SUMIFS(BASE_CALCULADA!K2:K1201,BASE_CALCULADA!X2:X1201,A4) -> 414272.65 | D4: =SUMIFS(BASE_CALCULADA!L2:L1201,BASE_CALCULADA!X2:X1201,A4) -> 184650.04 | E4: =IF(B4=0,0,ROUND(C4/B4,2)) -> 3395.68
A5: Elétrica | B5: =COUNTIF(BASE_CALCULADA!X2:X1201,A5) -> 142 | C5: =SUMIFS(BASE_CALCULADA!K2:K1201,BASE_CALCULADA!X2:X1201,A5) -> 499599.34 | D5: =SUMIFS(BASE_CALCULADA!L2:L1201,BASE_CALCULADA!X2:X1201,A5) -> 221995.45 | E5: =IF(B5=0,0,ROUND(C5/B5,2)) -> 3518.31
A6: Freios | B6: =COUNTIF(BASE_CALCULADA!X2:X1201,A6) -> 134 | C6: =SUMIFS(BASE_CALCULADA!K2:K1201,BASE_CALCULADA!X2:X1201,A6) -> 510555.79 | D6: =SUMIFS(BASE_CALCULADA!L2:L1201,BASE_CALCULADA!X2:X1201,A6) -> 228946.23 | E6: =IF(B6=0,0,ROUND(C6/B6,2)) -> 3810.12
A7: Funilaria | B7: =COUNTIF(BASE_CALCULADA!X2:X1201,A7) -> 127 | C7: =SUMIFS(BASE_CALCULADA!K2:K1201,BASE_CALCULADA!X2:X1201,A7) -> 394254.45 | D7: =SUMIFS(BASE_CALCULADA!L2:L1201,BASE_CALCULADA!X2:X1201,A7) -> 172890.14 | E7: =IF(B7=0,0,ROUND(C7/B7,2)) -> 3104.37
A8: Motor | B8: =COUNTIF(BASE_CALCULADA!X2:X1201,A8) -> 155 | C8: =SUMIFS(BASE_CALCULADA!K2:K1201,BASE_CALCULADA!X2:X1201,A8) -> 576258.22 | D8: =SUMIFS(BASE_CALCULADA!L2:L1201,BASE_CALCULADA!X2:X1201,A8) -> 255208.55 | E8: =IF(B8=0,0,ROUND(C8/B8,2)) -> 3717.79
A9: Pintura | B9: =COUNTIF(BASE_CALCULADA!X2:X1201,A9) -> 131 | C9: =SUMIFS(BASE_CALCULADA!K2:K1201,BASE_CALCULADA!X2:X1201,A9) -> 457418.18 | D9: =SUMIFS(BASE_CALCULADA!L2:L1201,BASE_CALCULADA!X2:X1201,A9) -> 201663.72 | E9: =IF(B9=0,0,ROUND(C9/B9,2)) -> 3491.74
A10: Revisão | B10: =COUNTIF(BASE_CALCULADA!X2:X1201,A10) -> 218 | C10: =SUMIFS(BASE_CALCULADA!K2:K1201,BASE_CALCULADA!X2:X1201,A10) -> 803684.53 | D10: =SUMIFS(BASE_CALCULADA!L2:L1201,BASE_CALCULADA!X2:X1201,A10) -> 355433.87 | E10: =IF(B10=0,0,ROUND(C10/B10,2)) -> 3686.63
A11: Suspensão | B11: =COUNTIF(BASE_CALCULADA!X2:X1201,A11) -> 171 | C11: =SUMIFS(BASE_CALCULADA!K2:K1201,BASE_CALCULADA!X2:X1201,A11) -> 621234.41 | D11: =SUMIFS(BASE_CALCULADA!L2:L1201,BASE_CALCULADA!X2:X1201,A11) -> 277940.66 | E11: =IF(B11=0,0,ROUND(C11/B11,2)) -> 3632.95

Sheet PREMISSAS
A1: PREMISSAS E NOTAS METODOLÓGICAS
A3: Parâmetro | B3: Valor | C3: Observação
A4: Markup médio de peças (%) | B4: =ROUND((AVERAGE(DIM_PECA!F2:F501)/AVERAGE(DIM_PECA!E2:E501)-1)*100,1) -> 75.9 | C4: Razão preço de venda / custo unitário, média simples sobre DIM_PECA
A5: Custo médio de mão de obra (R$) | B5: =ROUND(AVERAGE(BASE_CALCULADA!S2:S1201),2) -> 6645.05 | C5: Média da coluna valor_mao_obra_calc
A6: Margem operacional média (%) | B6: =ROUND(AVERAGE(BASE_CALCULADA!L2:L1201)/AVERAGE(BASE_CALCULADA!K2:K1201)*100,1) -> 44.4 | C6: Lucro médio / Receita média
A7: Preço de serviço médio (R$) | B7: =ROUND(AVERAGE(DIM_SERVICO!D2:D151),2) -> 1096.79 | C7: Média da preco_base em DIM_SERVICO
A8: Total de Ordens de Serviço na base | B8: 1200 | C8: Valor fixo - tamanho da base gerada
A9: Período coberto pelo calendário | B9: 01/01/2022 a 31/12/2026 | C9: DIM_TEMPO completa, dia a dia
A12: Notas metodológicas:
A13: 1. Todos os valores de receita, custo e lucro são expressos em Reais (R$).
A14: 2. As fórmulas PROCV referenciam diretamente as abas DIM_SERVICO e DIM_PECA desta mesma pasta de trabalho.
A15: 3. A coluna 'checagem' valida se o valor_total recalculado bate com o valor_total original (tolerância de 2 casas decimais via ARRED).
A16: 4. SUBTOTAL foi utilizado no RESUMO_KPIS para refletir corretamente contagens quando filtros são aplicados na tabela.
A17: 5. Esta base foi gerada de forma sintética para fins de modelagem, treinamento e prototipagem de Data Warehouse / BI; não representa dados reais de clientes.
